{
  "id": "demo@0.1.0",
  "nodes": {
    "35": {
      "id": 35,
      "data": {
        "expanded": true,
        "fnInAValue": 0,
        "fnInAValueType": "float",
        "fnInBValue": 0,
        "fnInBValueType": "float"
      },
      "inputs": {
        "fnInA": {
          "connections": [
            {
              "node": 36,
              "output": "fnOutA",
              "data": {}
            }
          ]
        },
        "fnInB": {
          "connections": [
            {
              "node": 50,
              "output": "out",
              "data": {}
            }
          ]
        }
      },
      "outputs": {},
      "blocks": [],
      "position": [
        550,
        0
      ],
      "name": "Output"
    },
    "36": {
      "id": 36,
      "data": {
        "assetValue": {
          "id": "devSubGraph",
          "label": "devSubGraph"
        },
        "assetValueType": "subgraph",
        "expanded": true,
        "preview": true,
        "fnInFloatValue": 0,
        "fnInFloatValueType": "float",
        "fnOutAValue": 0,
        "fnOutAValueType": "float",
        "fnOutBValue": 0,
        "fnOutBValueType": "float"
      },
      "inputs": {
        "fnInFloat": {
          "connections": [
            {
              "node": 45,
              "output": "out",
              "data": {}
            }
          ]
        }
      },
      "outputs": {
        "fnOutA": {
          "connections": [
            {
              "node": 35,
              "input": "fnInA",
              "data": {}
            }
          ]
        },
        "fnOutB": {
          "connections": [
            {
              "node": 50,
              "input": "a",
              "data": {}
            }
          ]
        }
      },
      "blocks": [],
      "position": [
        22.04513438034151,
        36.41879267508073
      ],
      "name": "SubGraph"
    },
    "45": {
      "id": 45,
      "data": {
        "outValue": 0,
        "outValueType": "float",
        "outValueName": "Float",
        "exposed": true,
        "expanded": true
      },
      "inputs": {},
      "outputs": {
        "out": {
          "connections": [
            {
              "node": 36,
              "input": "fnInFloat",
              "data": {}
            }
          ]
        }
      },
      "blocks": [],
      "position": [
        -214.05888805893213,
        109.1101190998395
      ],
      "name": "Parameter"
    },
    "50": {
      "id": 50,
      "data": {
        "aValue": 0,
        "aValueType": "float",
        "bValue": "2",
        "bValueType": "float",
        "outValue": 0,
        "outValueType": "float",
        "expanded": true,
        "preview": false
      },
      "inputs": {
        "a": {
          "connections": [
            {
              "node": 36,
              "output": "fnOutB",
              "data": {}
            }
          ]
        },
        "b": {
          "connections": []
        }
      },
      "outputs": {
        "out": {
          "connections": [
            {
              "node": 35,
              "input": "fnInB",
              "data": {}
            }
          ]
        }
      },
      "blocks": [],
      "position": [
        362.25633298840825,
        133.4116618923684
      ],
      "name": "Multiply"
    }
  },
  "UIState": {
    "showMainPreview": true,
    "showBlackBoard": true,
    "showInspector": true
  },
  "type": "SubGraph",
  "version": "0.0.0",
  "setting": {
    "template": "unlit",
    "precision": "single",
    "allowMaterialOverride": false,
    "surfaceType": "opaque",
    "blendingMode": "alpha",
    "renderFace": "front",
    "depthWrite": "auto",
    "depthTest": "l equal",
    "alphaClipping": false,
    "castShadows": true
  },
  "parameters": [
    {
      "name": "Float",
      "type": "float",
      "defalutValue": 0,
      "exposed": true
    }
  ]
}